{
"owner": [{"copyright":"authifyWeb https://github.com/authifyWeb"}],
"source":[
{"n":["Axis Bank"],"u":["www.axisbank.com","axisbank.com","omni.axisbank.co.in","application.axisbank.co.in","digiserv.axisbank.com","branch.axisbank.com","grabdeals.axisbank.com","twitter.com/axisbank"],"l":"https://raw.githubusercontent.com/authifyWeb/logos/main/logos/axisbank.svg","c":"Banking","o":"IN"},
{"n":["Internet Freedom Foundation"],"u":["internetfreedom.in","saveourprivacy.in","savetheinternet.in","patrakardefence.in","panoptic.in","twitter.com/internetfreedom","forum.internetfreedom.in"],"l":"https://raw.githubusercontent.com/authifyWeb/logos/main/logos/internetfreedomfoundation.svg","c":"Non Profit","o":"IN"},
{"n":["Bandhan Bank"],"u":["www.bandhanbank.com","bandhanbank.com","corporate.bandhanbank.com","sweb.gruh.com","gruh.com","www.gruh.com","twitter.com/bandhanbank_in"],"l":"https://raw.githubusercontent.com/authifyWeb/logos/main/logos/bandhanbank.svg","c":"Banking","o":"IN"},
{"n":["CSB Bank"],"u":["www.csb.co.in","csb.co.in","corpnet.csb.co.in","www.csbnet.co.in","csbnet.co.in"],"l":"https://raw.githubusercontent.com/authifyWeb/logos/main/logos/csbbank.svg","c":"Banking","o":"IN"},
{"n":["City Union Bank"],"u":["www.cityunionbank.com","cubltd.cityunionbank.in","cityunionbank.com"],"l":"https://raw.githubusercontent.com/authifyWeb/logos/main/logos/cityunionbank.svg","c":"Banking","o":"IN"},
{"n":["DCB Bank"],"u":["www.dcbbank.com","dcbbank.com","pib.dcbbank.com","edvportal.dcbbank.com","eazybee.dcbbank.com","genesis.dcbbank.com","twitter.com/dcbbank"],"l":"https://raw.githubusercontent.com/authifyWeb/logos/main/logos/dcbbank.svg","c":"Banking","o":"IN"},
{"n":["Dhanlaxmi Bank"],"u":["www.dhanbank.com","dhanbank.com","netbank.dhanbank.in"],"l":"https://raw.githubusercontent.com/authifyWeb/logos/main/logos/dhanlaxmibank.svg","c":"Banking","o":"IN"},
{"n":["Federal Bank"],"u":["www.federalbank.co.in","federalbank.co.in","fednetbank.com","www.fednetbank.com","fedebiz.federalbank.co.in","federemit.federalbank.co.in","fedcorp.federalbank.co.in","epay.federalbank.co.in","payments.federalbank.co.in","netcfastag.federalbank.co.in","accountopen.federalbank.co.in","portal.federalbank.co.in","twitter.com/federalbankltd","twitter.com/federalbankhelp"],"l":"https://raw.githubusercontent.com/authifyWeb/logos/main/logos/federalbank.svg","c":"Banking","o":"IN"},
{"n":["HDFC Bank"],"u":["www.hdfcbank.com","hdfcbank.com","v.hdfcbank.com","applyonline.hdfcbank.com","apply.hdfcbank.com","leads.hdfcbank.com","applycarloan.hdfcbank.com","offers.smartbuy.hdfcbank.com","twitter.com/hdfc_bank","netbanking.hdfcbank.com","hdfc_bank"],"l":"https://raw.githubusercontent.com/authifyWeb/logos/main/logos/hdfcbank.svg","c":"Banking","o":"IN"},
{"n":["ICICI Bank"],"u":["www.icicibank.com","icicibank.com","buy.icicibank.com","loans.icicibank.com","infinity.icicibank.com","nli.icicibank.com","loan.icicibank.com","twitter.com/icicibank_care","twitter.com/icicibank"],"l":"https://raw.githubusercontent.com/authifyWeb/logos/main/logos/icicibank.svg","c":"Banking","o":"IN"},
{"n":["IndusInd Bank"],"u":["www.indusind.com","indusind.com","bank.indusind.com","induseasywheels.indusind.com","myaccount.indusind.com","cfddealer.indusind.com","twitter.com/myindusindbank"],"l":"https://raw.githubusercontent.com/authifyWeb/logos/main/logos/indusindbank.svg","c":"Banking","o":"IN"},
{"n":["Jammu and Kashmir Bank","J&K Bank"],"u":["www.jkbank.com","www.jkbankonline.com","jkbankonline.com","jkbank.com","eapp.jkbank.com","ecollect.jkbank.com","twitter.com/jandkbank"],"l":"https://raw.githubusercontent.com/authifyWeb/logos/main/logos/jammuandkashmirbank.svg","c":"Banking","o":"IN"},
{"n":["Karnataka Bank"],"u":["karnatakabank.com","vcip.ktkbank.com","m.ktkbank.com","econnect.ktkbank.com","digiloan.ktkbank.com","twitter.com/karnatakabank"],"l":"https://github.com/authifyWeb/logos/raw/main/logos/karnatakabank.svg","c":"Banking","o":"IN"},
{"n":["Karur Vyasa Bank","KVB Bank"],"u":["www.kvb.co.in","kvb.co.in","www.karurvysyabank.co.in","prepaid.kvb.co.in","www.kvbankonline.com","twitter.com/karurvysyabank_","kvbprepaid.enstage.com","odr.kvb.co.in","www.kvbsmart.in"],"l":"https://raw.githubusercontent.com/authifyWeb/logos/main/logos/karurvysyabank.svg","c":"Banking","o":"IN"},
{"n":["Kotak Mahindra Bank"],"u":["www.kotak.com","kapps.kotak.com","kotak.com","kotakfastag.in","twitter.com/kotakbankltd","twitter.com/kotakcares"],"l":"https://raw.githubusercontent.com/authifyWeb/logos/main/logos/kotakmahindrabank.svg","c":"Banking","o":"IN"},
{"n":["Nainital Bank"],"u":["www.nainitalbank.co.in","nainitalbank.co.in","twitter.com/ltdnainital"],"l":"https://raw.githubusercontent.com/authifyWeb/logos/main/logos/nainitalbank.svg","c":"Banking","o":"IN"},
{"n":["RBL Bank"],"u":["www.rblbank.com","rblbank.com","abacus.rblbank.com","investment.rblbank.com","insignia.rblbank.com","isc.rblbank.com","ir.rblbank.com","blog.rblbank.com","twitter.com/rblbankcares","twitter.com/rblbank"],"l":"https://raw.githubusercontent.com/authifyWeb/logos/main/logos/rblbank.svg","c":"Banking","o":"IN"},
{"n":["South Indian Bank","SIB"],"u":["southindianbank.com","www.southindianbank.com","twitter.com/officialsibltd","feebook.southindianbank.com","online.southindianbank.com","fastag.southindianbank.com"],"l":"https://raw.githubusercontent.com/authifyWeb/logos/main/logos/southindianbank.svg","c":"Banking","o":"IN"},
{"n":["Tamilnad Mercantile Bank","TMB"],"u":["www.tmb.in","tmb.in","www.tmbnet.in","tmbnet.in","prepaid.tmbnet.in","www.tmbho.in","tmbho.in","twitter.com/tmbankltd"],"l":"https://raw.githubusercontent.com/authifyWeb/logos/main/logos/tamilnadmercantilebank.svg","c":"Banking","o":"IN"},
{"n":["Yes Bank"],"u":["www.yesbank.in","yesbank.in","campaignweb.yesbank.in","twitter.com/yesbank"],"l":"https://raw.githubusercontent.com/authifyWeb/logos/main/logos/yesbank.svg","c":"Banking","o":"IN"},
{"n":["IDBI Bank"],"u":["www.idbibank.in","idbibank.in","inet.idbibank.co.in","corp.idbibank.co.in","samriddhigsec.idbibank.co.in","idbicreditcards.co.in","clms.idbibank.co.in","secureonline.idbibank.com","apps.idbibank.in","idbiapps.idbibank.com","otsapplication.idbibank.com","webapps.idbibank.co.in","inetapps.idbibank.co.in","twitter.com/idbi_bank","twitter.com/idbibankcares"],"l":"https://raw.githubusercontent.com/authifyWeb/logos/main/logos/idbibank.svg","c":"Banking","o":"IN"},
{"n":["Bank of Baroda","BOB"],"u":["bankofbaroda.co.in","www.bankofbaroda.in","bankofbaroda.in","ifsc.bankofbaroda.in","twitter.com/bankofbaroda","bobcrm.bankofbaroda.co.in","tabit.bankofbaroda.com","bankofbaroda.com","dil.bankofbaroda.in","www.bobworld.com","bobworld.com","apps.bobinside.com"],"l":"https://raw.githubusercontent.com/authifyWeb/logos/main/logos/bankofbaroda.svg","c":"Banking","o":"IN"},
{"n":["Bank of India"],"u":["www.bankofindia.co.in","bankofindia.co.in","uat.corp.bankofindiaweb.com","boiweb.bankofindia.co.in","twitter.com/bankofindia_in"],"l":"https://raw.githubusercontent.com/authifyWeb/logos/main/logos/bankofindia.svg","c":"Banking","o":"IN"},
{"n":["Bank of Maharashtra"],"u":["bankofmaharashtra.in","www.bankofmaharashtra.in","www.mahaconnect.in","mahaconnect.in","www.bomloans.com","bomloans.com","digiloans.bankofmaharashtra.in","twitter.com/mahabank","onlinebanking.bankofmaharashtra.in","reward.bankofmaharashtra.in","bomsurvey.com","branch-atm-locator.bankofmaharashtra.in"],"l":"https://raw.githubusercontent.com/authifyWeb/logos/main/logos/bankofmaharashtra.svg","c":"Banking","o":"IN"},
{"n":["Canara Bank"],"u":["canarabank.com","www.canarabank.com","canaramsme.in","www.canaramsme.in","canarabankcsis.in","www.canarabankcsis.in","odr.canarabank.com","online.canarabank.in","canmoneyonline.com","www.canmoneyonline.com","ccapp.canarabank.in","canepaycustoms.canarabank.in","twitter.com/canarabank"],"l":"https://raw.githubusercontent.com/authifyWeb/logos/main/logos/canarabank.svg","c":"Banking","o":"IN"},
{"n":["Central Bank of India"],"u":["centralbankofindia.co.in","www.centralbankofindia.co.in","twitter.com/centralbank_in","centralbank.net.in","www.centralbank.net.in","vkyc.centralbank.co.in"],"l":"https://raw.githubusercontent.com/authifyWeb/logos/main/logos/centralbankofindia.svg","c":"Banking","o":"IN"},
{"n":["Indian Bank"],"u":["indianbank.in","www.indianbank.in","apps.indianbank.in","onlinellms.indianbank.in","indadvantage.com","www.indadvantage.com","twitter.com/myindianbank"],"l":"https://raw.githubusercontent.com/authifyWeb/logos/main/logos/indianbank.svg","c":"Banking","o":"IN"},
{"n":["Indian Overseas Bank","IOB"],"u":["www.iob.in","iob.in","www.iobnet.co.in","vkyc.iob.in","twitter.com/iobindia"],"l":"https://raw.githubusercontent.com/authifyWeb/logos/main/logos/indianoverseasbank.svg","c":"Banking","o":"IN"},
{"n":["Punjab & Sind Bank"],"u":["punjabandsindbank.co.in","www.punjabandsindbank.co.in","twitter.com/psbindOfficial"],"l":"https://raw.githubusercontent.com/authifyWeb/logos/main/logos/punjabandsindbank.svg","c":"Banking","o":"IN"},
{"n":["Punjab National Bank - PNB"],"u":["www.pnbindia.in","pnbindia.in","pnbcard.in","www.pnbcard.in","apply.pnbcard.in","gateway.pnbibanking.in","pnbibanking.in","www.pnbibanking.in","www.netpnb.com","netpnb.com","twitter.com/pnbindia","weblens.pnb.in","instaloans.pnbindia.in","eots.mypnb.in","onlinesb.pnbindia.in"],"l":"https://raw.githubusercontent.com/authifyWeb/logos/main/logos/punjabnationalbank.svg","c":"Banking","o":"IN"},
{"n":["State Bank of India","SBI"],"u":["www.sbi.co.in","sbi.co.in","mobilityretail.sbi","retail.onlinesbi.sbi","homeloans.sbi","onlinesbi.sbi","www.onlinesbi.sbi","bank.sbi","twitter.com/theofficialsbi"],"l":"https://raw.githubusercontent.com/authifyWeb/logos/main/logos/statebankofindia.svg","c":"Banking","o":"IN"},
{"n":["UCO Bank"],"u":["www.ucobank.com","ucobank.com","smartpay.ucoonline.in","twitter.com/ucobankofficial"],"l":"https://raw.githubusercontent.com/authifyWeb/logos/main/logos/ucobank.svg","c":"Banking","o":"IN"},
{"n":["Union Bank of India"],"u":["www.unionbankonline.co.in","unionbankonline.co.in","twitter.com/unionbanktweets"],"l":"https://raw.githubusercontent.com/authifyWeb/logos/main/logos/unionbankofindia.svg","c":"Banking","o":"IN"}

]
}
  
